[
  {
    "inputBlock": 131324,
    "outputBlock": 131373
  },
  {
    "inputBlock": 131374,
    "outputBlock": 131423
  },
  {
    "inputBlock": 131424,
    "outputBlock": 131473
  },
  {
    "inputBlock": 131474,
    "outputBlock": 131523
  },
  {
    "inputBlock": 131524,
    "outputBlock": 131573
  },
  {
    "inputBlock": 131574,
    "outputBlock": 131623
  },
  {
    "inputBlock": 131624,
    "outputBlock": 131673
  },
  {
    "inputBlock": 131674,
    "outputBlock": 131723
  },
  {
    "inputBlock": 131724,
    "outputBlock": 131773
  },
  {
    "inputBlock": 131774,
    "outputBlock": 131823
  },
  {
    "inputBlock": 131824,
    "outputBlock": 131873
  },
  {
    "inputBlock": 131874,
    "outputBlock": 131923
  },
  {
    "inputBlock": 131924,
    "outputBlock": 131973
  },
  {
    "inputBlock": 131974,
    "outputBlock": 132023
  },
  {
    "inputBlock": 132024,
    "outputBlock": 132073
  },
  {
    "inputBlock": 132074,
    "outputBlock": 132123
  },
  {
    "inputBlock": 132124,
    "outputBlock": 132173
  },
  {
    "inputBlock": 132174,
    "outputBlock": 132223
  },
  {
    "inputBlock": 132224,
    "outputBlock": 132273
  },
  {
    "inputBlock": 132274,
    "outputBlock": 132323
  },
  {
    "inputBlock": 132324,
    "outputBlock": 132373
  },
  {
    "inputBlock": 132374,
    "outputBlock": 132423
  },
  {
    "inputBlock": 132424,
    "outputBlock": 132473
  },
  {
    "inputBlock": 132474,
    "outputBlock": 132523
  },
  {
    "inputBlock": 132524,
    "outputBlock": 132573
  },
  {
    "inputBlock": 132574,
    "outputBlock": 132623
  },
  {
    "inputBlock": 132624,
    "outputBlock": 132673
  },
  {
    "inputBlock": 132674,
    "outputBlock": 132723
  },
  {
    "inputBlock": 132724,
    "outputBlock": 132773
  },
  {
    "inputBlock": 132774,
    "outputBlock": 132823
  },
  {
    "inputBlock": 132824,
    "outputBlock": 132873
  },
  {
    "inputBlock": 132874,
    "outputBlock": 132923
  },
  {
    "inputBlock": 132924,
    "outputBlock": 132973
  },
  {
    "inputBlock": 132974,
    "outputBlock": 133023
  },
  {
    "inputBlock": 133024,
    "outputBlock": 133073
  },
  {
    "inputBlock": 133074,
    "outputBlock": 133123
  },
  {
    "inputBlock": 133124,
    "outputBlock": 133173
  },
  {
    "inputBlock": 133174,
    "outputBlock": 133223
  },
  {
    "inputBlock": 133224,
    "outputBlock": 133273
  },
  {
    "inputBlock": 133274,
    "outputBlock": 133323
  },
  {
    "inputBlock": 133324,
    "outputBlock": 133373
  },
  {
    "inputBlock": 133374,
    "outputBlock": 133423
  },
  {
    "inputBlock": 133424,
    "outputBlock": 133473
  },
  {
    "inputBlock": 133474,
    "outputBlock": 133523
  },
  {
    "inputBlock": 133524,
    "outputBlock": 133573
  },
  {
    "inputBlock": 133574,
    "outputBlock": 133623
  },
  {
    "inputBlock": 133624,
    "outputBlock": 133673
  },
  {
    "inputBlock": 133674,
    "outputBlock": 133723
  },
  {
    "inputBlock": 133724,
    "outputBlock": 133773
  },
  {
    "inputBlock": 133774,
    "outputBlock": 133823
  },
  {
    "inputBlock": 133824,
    "outputBlock": 133873
  },
  {
    "inputBlock": 133874,
    "outputBlock": 133923
  },
  {
    "inputBlock": 133924,
    "outputBlock": 133973
  },
  {
    "inputBlock": 133974,
    "outputBlock": 134023
  },
  {
    "inputBlock": 134024,
    "outputBlock": 134073
  },
  {
    "inputBlock": 134074,
    "outputBlock": 134123
  },
  {
    "inputBlock": 134124,
    "outputBlock": 134173
  },
  {
    "inputBlock": 134174,
    "outputBlock": 134223
  },
  {
    "inputBlock": 134224,
    "outputBlock": 134273
  },
  {
    "inputBlock": 134274,
    "outputBlock": 134323
  },
  {
    "inputBlock": 134324,
    "outputBlock": 134373
  },
  {
    "inputBlock": 134374,
    "outputBlock": 134423
  },
  {
    "inputBlock": 134424,
    "outputBlock": 134473
  },
  {
    "inputBlock": 134474,
    "outputBlock": 134523
  },
  {
    "inputBlock": 134524,
    "outputBlock": 134598
  },
  {
    "inputBlock": 134599,
    "outputBlock": 134673
  },
  {
    "inputBlock": 134674,
    "outputBlock": 134748
  },
  {
    "inputBlock": 134749,
    "outputBlock": 134823
  },
  {
    "inputBlock": 134824,
    "outputBlock": 134898
  },
  {
    "inputBlock": 134899,
    "outputBlock": 134973
  },
  {
    "inputBlock": 134974,
    "outputBlock": 135048
  },
  {
    "inputBlock": 135049,
    "outputBlock": 135123
  },
  {
    "inputBlock": 135124,
    "outputBlock": 135198
  },
  {
    "inputBlock": 135199,
    "outputBlock": 135273
  },
  {
    "inputBlock": 135274,
    "outputBlock": 135348
  },
  {
    "inputBlock": 135349,
    "outputBlock": 135423
  },
  {
    "inputBlock": 135424,
    "outputBlock": 135498
  },
  {
    "inputBlock": 135499,
    "outputBlock": 135573
  },
  {
    "inputBlock": 135574,
    "outputBlock": 135648
  },
  {
    "inputBlock": 135649,
    "outputBlock": 135723
  },
  {
    "inputBlock": 135724,
    "outputBlock": 135798
  },
  {
    "inputBlock": 135799,
    "outputBlock": 135873
  },
  {
    "inputBlock": 135874,
    "outputBlock": 135948
  },
  {
    "inputBlock": 135949,
    "outputBlock": 136023
  },
  {
    "inputBlock": 136024,
    "outputBlock": 136098
  },
  {
    "inputBlock": 136099,
    "outputBlock": 136173
  },
  {
    "inputBlock": 136174,
    "outputBlock": 136248
  },
  {
    "inputBlock": 136249,
    "outputBlock": 136323
  },
  {
    "inputBlock": 136324,
    "outputBlock": 136398
  },
  {
    "inputBlock": 136399,
    "outputBlock": 136473
  },
  {
    "inputBlock": 136474,
    "outputBlock": 136548
  },
  {
    "inputBlock": 136549,
    "outputBlock": 136623
  },
  {
    "inputBlock": 136624,
    "outputBlock": 136698
  },
  {
    "inputBlock": 136699,
    "outputBlock": 136773
  },
  {
    "inputBlock": 136774,
    "outputBlock": 136848
  },
  {
    "inputBlock": 136849,
    "outputBlock": 136923
  },
  {
    "inputBlock": 136924,
    "outputBlock": 136998
  },
  {
    "inputBlock": 136999,
    "outputBlock": 137073
  },
  {
    "inputBlock": 137074,
    "outputBlock": 137148
  },
  {
    "inputBlock": 137149,
    "outputBlock": 137223
  },
  {
    "inputBlock": 137224,
    "outputBlock": 137298
  },
  {
    "inputBlock": 137299,
    "outputBlock": 137373
  },
  {
    "inputBlock": 137374,
    "outputBlock": 137448
  },
  {
    "inputBlock": 137449,
    "outputBlock": 137523
  },
  {
    "inputBlock": 137524,
    "outputBlock": 137598
  },
  {
    "inputBlock": 137599,
    "outputBlock": 137673
  },
  {
    "inputBlock": 137674,
    "outputBlock": 137748
  },
  {
    "inputBlock": 137749,
    "outputBlock": 137823
  },
  {
    "inputBlock": 137824,
    "outputBlock": 137898
  },
  {
    "inputBlock": 137899,
    "outputBlock": 137973
  },
  {
    "inputBlock": 137974,
    "outputBlock": 138048
  },
  {
    "inputBlock": 138049,
    "outputBlock": 138123
  },
  {
    "inputBlock": 138124,
    "outputBlock": 138198
  },
  {
    "inputBlock": 138199,
    "outputBlock": 138273
  },
  {
    "inputBlock": 138274,
    "outputBlock": 138348
  },
  {
    "inputBlock": 138349,
    "outputBlock": 138423
  },
  {
    "inputBlock": 138424,
    "outputBlock": 138498
  },
  {
    "inputBlock": 138499,
    "outputBlock": 138573
  },
  {
    "inputBlock": 138574,
    "outputBlock": 138648
  },
  {
    "inputBlock": 138649,
    "outputBlock": 138723
  },
  {
    "inputBlock": 138724,
    "outputBlock": 138798
  },
  {
    "inputBlock": 138799,
    "outputBlock": 138873
  },
  {
    "inputBlock": 138874,
    "outputBlock": 138948
  },
  {
    "inputBlock": 138949,
    "outputBlock": 139023
  },
  {
    "inputBlock": 139024,
    "outputBlock": 139098
  },
  {
    "inputBlock": 139099,
    "outputBlock": 139173
  },
  {
    "inputBlock": 139174,
    "outputBlock": 139248
  },
  {
    "inputBlock": 139249,
    "outputBlock": 139323
  },
  {
    "inputBlock": 139324,
    "outputBlock": 139398
  },
  {
    "inputBlock": 139399,
    "outputBlock": 139473
  },
  {
    "inputBlock": 139474,
    "outputBlock": 139548
  },
  {
    "inputBlock": 139549,
    "outputBlock": 139623
  },
  {
    "inputBlock": 139624,
    "outputBlock": 139698
  },
  {
    "inputBlock": 139699,
    "outputBlock": 139773
  },
  {
    "inputBlock": 139774,
    "outputBlock": 139848
  },
  {
    "inputBlock": 139849,
    "outputBlock": 139923
  },
  {
    "inputBlock": 139924,
    "outputBlock": 139998
  },
  {
    "inputBlock": 139999,
    "outputBlock": 140073
  },
  {
    "inputBlock": 140074,
    "outputBlock": 140148
  },
  {
    "inputBlock": 140149,
    "outputBlock": 140223
  },
  {
    "inputBlock": 140224,
    "outputBlock": 140298
  },
  {
    "inputBlock": 140299,
    "outputBlock": 140373
  },
  {
    "inputBlock": 140374,
    "outputBlock": 140448
  },
  {
    "inputBlock": 140449,
    "outputBlock": 140523
  },
  {
    "inputBlock": 140524,
    "outputBlock": 140598
  },
  {
    "inputBlock": 140599,
    "outputBlock": 140673
  },
  {
    "inputBlock": 140674,
    "outputBlock": 140773
  },
  {
    "inputBlock": 140774,
    "outputBlock": 140873
  },
  {
    "inputBlock": 140874,
    "outputBlock": 140973
  },
  {
    "inputBlock": 140974,
    "outputBlock": 141073
  },
  {
    "inputBlock": 141074,
    "outputBlock": 141173
  },
  {
    "inputBlock": 141174,
    "outputBlock": 141273
  },
  {
    "inputBlock": 141274,
    "outputBlock": 141373
  },
  {
    "inputBlock": 141374,
    "outputBlock": 141473
  },
  {
    "inputBlock": 141474,
    "outputBlock": 141573
  },
  {
    "inputBlock": 141574,
    "outputBlock": 141673
  },
  {
    "inputBlock": 141674,
    "outputBlock": 141773
  },
  {
    "inputBlock": 141774,
    "outputBlock": 141873
  },
  {
    "inputBlock": 141874,
    "outputBlock": 141973
  },
  {
    "inputBlock": 141974,
    "outputBlock": 142073
  },
  {
    "inputBlock": 142074,
    "outputBlock": 142173
  },
  {
    "inputBlock": 142174,
    "outputBlock": 142273
  },
  {
    "inputBlock": 142274,
    "outputBlock": 142373
  },
  {
    "inputBlock": 142374,
    "outputBlock": 142473
  },
  {
    "inputBlock": 142474,
    "outputBlock": 142573
  },
  {
    "inputBlock": 142574,
    "outputBlock": 142673
  },
  {
    "inputBlock": 142674,
    "outputBlock": 142773
  },
  {
    "inputBlock": 142774,
    "outputBlock": 142873
  },
  {
    "inputBlock": 142874,
    "outputBlock": 142973
  },
  {
    "inputBlock": 142974,
    "outputBlock": 143073
  },
  {
    "inputBlock": 143074,
    "outputBlock": 143173
  },
  {
    "inputBlock": 143174,
    "outputBlock": 143273
  },
  {
    "inputBlock": 143274,
    "outputBlock": 143373
  },
  {
    "inputBlock": 143374,
    "outputBlock": 143473
  },
  {
    "inputBlock": 143474,
    "outputBlock": 143573
  },
  {
    "inputBlock": 143574,
    "outputBlock": 143673
  },
  {
    "inputBlock": 143674,
    "outputBlock": 143773
  },
  {
    "inputBlock": 143774,
    "outputBlock": 143873
  },
  {
    "inputBlock": 143874,
    "outputBlock": 143973
  },
  {
    "inputBlock": 143974,
    "outputBlock": 144073
  },
  {
    "inputBlock": 144074,
    "outputBlock": 144173
  },
  {
    "inputBlock": 144174,
    "outputBlock": 144273
  },
  {
    "inputBlock": 144274,
    "outputBlock": 144373
  },
  {
    "inputBlock": 144374,
    "outputBlock": 144473
  },
  {
    "inputBlock": 144474,
    "outputBlock": 144573
  },
  {
    "inputBlock": 144574,
    "outputBlock": 144673
  },
  {
    "inputBlock": 144674,
    "outputBlock": 144773
  },
  {
    "inputBlock": 144774,
    "outputBlock": 144873
  },
  {
    "inputBlock": 144874,
    "outputBlock": 144973
  },
  {
    "inputBlock": 144974,
    "outputBlock": 145073
  },
  {
    "inputBlock": 145074,
    "outputBlock": 145173
  },
  {
    "inputBlock": 145174,
    "outputBlock": 145273
  },
  {
    "inputBlock": 145274,
    "outputBlock": 145373
  },
  {
    "inputBlock": 145374,
    "outputBlock": 145473
  },
  {
    "inputBlock": 145474,
    "outputBlock": 145573
  },
  {
    "inputBlock": 145574,
    "outputBlock": 145673
  },
  {
    "inputBlock": 145674,
    "outputBlock": 145773
  },
  {
    "inputBlock": 145774,
    "outputBlock": 145873
  },
  {
    "inputBlock": 145874,
    "outputBlock": 145973
  },
  {
    "inputBlock": 145974,
    "outputBlock": 146073
  },
  {
    "inputBlock": 146074,
    "outputBlock": 146173
  },
  {
    "inputBlock": 146174,
    "outputBlock": 146273
  },
  {
    "inputBlock": 146274,
    "outputBlock": 146373
  },
  {
    "inputBlock": 146374,
    "outputBlock": 146473
  },
  {
    "inputBlock": 146474,
    "outputBlock": 146573
  },
  {
    "inputBlock": 146574,
    "outputBlock": 146673
  },
  {
    "inputBlock": 146674,
    "outputBlock": 146773
  },
  {
    "inputBlock": 146774,
    "outputBlock": 146873
  },
  {
    "inputBlock": 146874,
    "outputBlock": 146973
  },
  {
    "inputBlock": 146974,
    "outputBlock": 147073
  },
  {
    "inputBlock": 147074,
    "outputBlock": 147173
  },
  {
    "inputBlock": 147174,
    "outputBlock": 147273
  },
  {
    "inputBlock": 147274,
    "outputBlock": 147373
  },
  {
    "inputBlock": 147374,
    "outputBlock": 147473
  },
  {
    "inputBlock": 147474,
    "outputBlock": 147573
  },
  {
    "inputBlock": 147574,
    "outputBlock": 147673
  },
  {
    "inputBlock": 147674,
    "outputBlock": 147773
  },
  {
    "inputBlock": 147774,
    "outputBlock": 147873
  },
  {
    "inputBlock": 147874,
    "outputBlock": 147973
  },
  {
    "inputBlock": 147974,
    "outputBlock": 148073
  },
  {
    "inputBlock": 148074,
    "outputBlock": 148173
  },
  {
    "inputBlock": 148174,
    "outputBlock": 148273
  },
  {
    "inputBlock": 148274,
    "outputBlock": 148373
  },
  {
    "inputBlock": 148374,
    "outputBlock": 148473
  },
  {
    "inputBlock": 148474,
    "outputBlock": 148573
  },
  {
    "inputBlock": 148574,
    "outputBlock": 148673
  },
  {
    "inputBlock": 148674,
    "outputBlock": 148773
  },
  {
    "inputBlock": 148774,
    "outputBlock": 148873
  },
  {
    "inputBlock": 148874,
    "outputBlock": 148973
  },
  {
    "inputBlock": 148974,
    "outputBlock": 149073
  },
  {
    "inputBlock": 149074,
    "outputBlock": 149173
  },
  {
    "inputBlock": 149174,
    "outputBlock": 149273
  },
  {
    "inputBlock": 149274,
    "outputBlock": 149373
  },
  {
    "inputBlock": 149374,
    "outputBlock": 149473
  },
  {
    "inputBlock": 149474,
    "outputBlock": 149573
  },
  {
    "inputBlock": 149574,
    "outputBlock": 149673
  },
  {
    "inputBlock": 149674,
    "outputBlock": 149773
  },
  {
    "inputBlock": 149774,
    "outputBlock": 149873
  },
  {
    "inputBlock": 149874,
    "outputBlock": 149973
  },
  {
    "inputBlock": 149974,
    "outputBlock": 150073
  },
  {
    "inputBlock": 150074,
    "outputBlock": 150173
  },
  {
    "inputBlock": 150174,
    "outputBlock": 150273
  },
  {
    "inputBlock": 150274,
    "outputBlock": 150373
  },
  {
    "inputBlock": 150374,
    "outputBlock": 150473
  },
  {
    "inputBlock": 150474,
    "outputBlock": 150573
  },
  {
    "inputBlock": 150574,
    "outputBlock": 150673
  },
  {
    "inputBlock": 150674,
    "outputBlock": 150773
  },
  {
    "inputBlock": 150774,
    "outputBlock": 150873
  },
  {
    "inputBlock": 150874,
    "outputBlock": 150973
  },
  {
    "inputBlock": 150974,
    "outputBlock": 151073
  },
  {
    "inputBlock": 151074,
    "outputBlock": 151173
  },
  {
    "inputBlock": 151174,
    "outputBlock": 151273
  },
  {
    "inputBlock": 151274,
    "outputBlock": 151373
  },
  {
    "inputBlock": 151374,
    "outputBlock": 151473
  },
  {
    "inputBlock": 151474,
    "outputBlock": 151573
  },
  {
    "inputBlock": 151574,
    "outputBlock": 151673
  },
  {
    "inputBlock": 151674,
    "outputBlock": 151773
  },
  {
    "inputBlock": 151774,
    "outputBlock": 151873
  },
  {
    "inputBlock": 151874,
    "outputBlock": 151973
  },
  {
    "inputBlock": 151974,
    "outputBlock": 152073
  },
  {
    "inputBlock": 152074,
    "outputBlock": 152173
  },
  {
    "inputBlock": 152174,
    "outputBlock": 152273
  },
  {
    "inputBlock": 152274,
    "outputBlock": 152373
  },
  {
    "inputBlock": 152374,
    "outputBlock": 152473
  },
  {
    "inputBlock": 152474,
    "outputBlock": 152573
  },
  {
    "inputBlock": 152574,
    "outputBlock": 152673
  },
  {
    "inputBlock": 152674,
    "outputBlock": 152773
  },
  {
    "inputBlock": 152774,
    "outputBlock": 152873
  },
  {
    "inputBlock": 152874,
    "outputBlock": 152973
  },
  {
    "inputBlock": 152974,
    "outputBlock": 153073
  },
  {
    "inputBlock": 153074,
    "outputBlock": 153173
  },
  {
    "inputBlock": 153174,
    "outputBlock": 153273
  },
  {
    "inputBlock": 153274,
    "outputBlock": 153373
  },
  {
    "inputBlock": 153374,
    "outputBlock": 153473
  },
  {
    "inputBlock": 153474,
    "outputBlock": 153573
  },
  {
    "inputBlock": 153574,
    "outputBlock": 153673
  },
  {
    "inputBlock": 153674,
    "outputBlock": 153773
  },
  {
    "inputBlock": 153774,
    "outputBlock": 153873
  },
  {
    "inputBlock": 153874,
    "outputBlock": 153973
  },
  {
    "inputBlock": 153974,
    "outputBlock": 154073
  },
  {
    "inputBlock": 154074,
    "outputBlock": 154173
  },
  {
    "inputBlock": 154174,
    "outputBlock": 154273
  },
  {
    "inputBlock": 154274,
    "outputBlock": 154373
  },
  {
    "inputBlock": 154374,
    "outputBlock": 154473
  },
  {
    "inputBlock": 154474,
    "outputBlock": 154573
  },
  {
    "inputBlock": 154574,
    "outputBlock": 154673
  },
  {
    "inputBlock": 154674,
    "outputBlock": 154773
  },
  {
    "inputBlock": 154774,
    "outputBlock": 154873
  },
  {
    "inputBlock": 154874,
    "outputBlock": 154973
  },
  {
    "inputBlock": 154974,
    "outputBlock": 155073
  },
  {
    "inputBlock": 155074,
    "outputBlock": 155173
  },
  {
    "inputBlock": 155174,
    "outputBlock": 155273
  },
  {
    "inputBlock": 155274,
    "outputBlock": 155373
  },
  {
    "inputBlock": 155374,
    "outputBlock": 155473
  },
  {
    "inputBlock": 155474,
    "outputBlock": 155573
  },
  {
    "inputBlock": 155574,
    "outputBlock": 155673
  },
  {
    "inputBlock": 155674,
    "outputBlock": 155773
  },
  {
    "inputBlock": 155774,
    "outputBlock": 155873
  },
  {
    "inputBlock": 155874,
    "outputBlock": 155973
  },
  {
    "inputBlock": 155974,
    "outputBlock": 156073
  },
  {
    "inputBlock": 156074,
    "outputBlock": 156173
  },
  {
    "inputBlock": 156174,
    "outputBlock": 156273
  },
  {
    "inputBlock": 156274,
    "outputBlock": 156373
  },
  {
    "inputBlock": 156374,
    "outputBlock": 156473
  },
  {
    "inputBlock": 156474,
    "outputBlock": 156573
  },
  {
    "inputBlock": 156574,
    "outputBlock": 156673
  },
  {
    "inputBlock": 156674,
    "outputBlock": 156773
  },
  {
    "inputBlock": 156774,
    "outputBlock": 156873
  },
  {
    "inputBlock": 156874,
    "outputBlock": 156973
  },
  {
    "inputBlock": 156974,
    "outputBlock": 157073
  },
  {
    "inputBlock": 157074,
    "outputBlock": 157173
  },
  {
    "inputBlock": 157174,
    "outputBlock": 157273
  },
  {
    "inputBlock": 157274,
    "outputBlock": 157373
  },
  {
    "inputBlock": 157374,
    "outputBlock": 157473
  },
  {
    "inputBlock": 157474,
    "outputBlock": 157573
  },
  {
    "inputBlock": 157574,
    "outputBlock": 157673
  },
  {
    "inputBlock": 157674,
    "outputBlock": 157773
  },
  {
    "inputBlock": 157774,
    "outputBlock": 157873
  },
  {
    "inputBlock": 157874,
    "outputBlock": 157973
  },
  {
    "inputBlock": 157974,
    "outputBlock": 158073
  },
  {
    "inputBlock": 158074,
    "outputBlock": 158173
  },
  {
    "inputBlock": 158174,
    "outputBlock": 158273
  },
  {
    "inputBlock": 158274,
    "outputBlock": 158373
  },
  {
    "inputBlock": 158374,
    "outputBlock": 158473
  },
  {
    "inputBlock": 158474,
    "outputBlock": 158573
  },
  {
    "inputBlock": 158574,
    "outputBlock": 158673
  },
  {
    "inputBlock": 158674,
    "outputBlock": 158773
  },
  {
    "inputBlock": 158774,
    "outputBlock": 158873
  },
  {
    "inputBlock": 158874,
    "outputBlock": 158973
  },
  {
    "inputBlock": 158974,
    "outputBlock": 159073
  },
  {
    "inputBlock": 159074,
    "outputBlock": 159173
  },
  {
    "inputBlock": 159174,
    "outputBlock": 159273
  },
  {
    "inputBlock": 159274,
    "outputBlock": 159373
  },
  {
    "inputBlock": 159374,
    "outputBlock": 159473
  },
  {
    "inputBlock": 159474,
    "outputBlock": 159573
  },
  {
    "inputBlock": 159574,
    "outputBlock": 159673
  },
  {
    "inputBlock": 159674,
    "outputBlock": 159773
  },
  {
    "inputBlock": 159774,
    "outputBlock": 159873
  },
  {
    "inputBlock": 159874,
    "outputBlock": 159973
  },
  {
    "inputBlock": 159974,
    "outputBlock": 160071
  },
  {
    "inputBlock": 160072,
    "outputBlock": 160171
  },
  {
    "inputBlock": 160172,
    "outputBlock": 160271
  },
  {
    "inputBlock": 160272,
    "outputBlock": 160371
  },
  {
    "inputBlock": 160372,
    "outputBlock": 160471
  },
  {
    "inputBlock": 160472,
    "outputBlock": 160571
  },
  {
    "inputBlock": 160572,
    "outputBlock": 160671
  },
  {
    "inputBlock": 160672,
    "outputBlock": 160771
  },
  {
    "inputBlock": 160772,
    "outputBlock": 160871
  },
  {
    "inputBlock": 160872,
    "outputBlock": 160971
  },
  {
    "inputBlock": 160972,
    "outputBlock": 161071
  },
  {
    "inputBlock": 161072,
    "outputBlock": 161171
  },
  {
    "inputBlock": 161172,
    "outputBlock": 161271
  },
  {
    "inputBlock": 161272,
    "outputBlock": 161371
  },
  {
    "inputBlock": 161372,
    "outputBlock": 161471
  },
  {
    "inputBlock": 161472,
    "outputBlock": 161571
  },
  {
    "inputBlock": 161572,
    "outputBlock": 161671
  },
  {
    "inputBlock": 161672,
    "outputBlock": 161771
  },
  {
    "inputBlock": 161772,
    "outputBlock": 161871
  },
  {
    "inputBlock": 161872,
    "outputBlock": 161971
  },
  {
    "inputBlock": 161972,
    "outputBlock": 162071
  },
  {
    "inputBlock": 162072,
    "outputBlock": 162171
  },
  {
    "inputBlock": 162172,
    "outputBlock": 162271
  },
  {
    "inputBlock": 162272,
    "outputBlock": 162371
  },
  {
    "inputBlock": 162372,
    "outputBlock": 162471
  },
  {
    "inputBlock": 162472,
    "outputBlock": 162571
  },
  {
    "inputBlock": 162572,
    "outputBlock": 162671
  },
  {
    "inputBlock": 162672,
    "outputBlock": 162771
  },
  {
    "inputBlock": 162772,
    "outputBlock": 162865
  },
  {
    "inputBlock": 162866,
    "outputBlock": 162963
  },
  {
    "inputBlock": 162964,
    "outputBlock": 163063
  },
  {
    "inputBlock": 163064,
    "outputBlock": 163163
  },
  {
    "inputBlock": 163164,
    "outputBlock": 163263
  },
  {
    "inputBlock": 163264,
    "outputBlock": 163363
  },
  {
    "inputBlock": 163364,
    "outputBlock": 163463
  },
  {
    "inputBlock": 163464,
    "outputBlock": 163563
  },
  {
    "inputBlock": 163564,
    "outputBlock": 163663
  },
  {
    "inputBlock": 163664,
    "outputBlock": 163763
  },
  {
    "inputBlock": 163764,
    "outputBlock": 163863
  },
  {
    "inputBlock": 163864,
    "outputBlock": 163963
  },
  {
    "inputBlock": 163964,
    "outputBlock": 164063
  },
  {
    "inputBlock": 164064,
    "outputBlock": 164163
  },
  {
    "inputBlock": 164164,
    "outputBlock": 164263
  },
  {
    "inputBlock": 164264,
    "outputBlock": 164363
  },
  {
    "inputBlock": 164364,
    "outputBlock": 164463
  },
  {
    "inputBlock": 164464,
    "outputBlock": 164563
  },
  {
    "inputBlock": 164564,
    "outputBlock": 164663
  },
  {
    "inputBlock": 164664,
    "outputBlock": 164763
  },
  {
    "inputBlock": 164764,
    "outputBlock": 164863
  },
  {
    "inputBlock": 164864,
    "outputBlock": 164963
  },
  {
    "inputBlock": 164964,
    "outputBlock": 165063
  },
  {
    "inputBlock": 165064,
    "outputBlock": 165163
  },
  {
    "inputBlock": 165164,
    "outputBlock": 165263
  },
  {
    "inputBlock": 165264,
    "outputBlock": 165363
  },
  {
    "inputBlock": 165364,
    "outputBlock": 165463
  },
  {
    "inputBlock": 165464,
    "outputBlock": 165563
  },
  {
    "inputBlock": 165564,
    "outputBlock": 165663
  },
  {
    "inputBlock": 165664,
    "outputBlock": 165763
  },
  {
    "inputBlock": 165764,
    "outputBlock": 165863
  },
  {
    "inputBlock": 165864,
    "outputBlock": 165963
  },
  {
    "inputBlock": 165964,
    "outputBlock": 166063
  },
  {
    "inputBlock": 166064,
    "outputBlock": 166163
  },
  {
    "inputBlock": 166164,
    "outputBlock": 166263
  },
  {
    "inputBlock": 166264,
    "outputBlock": 166363
  },
  {
    "inputBlock": 166364,
    "outputBlock": 166463
  },
  {
    "inputBlock": 166464,
    "outputBlock": 166563
  },
  {
    "inputBlock": 166564,
    "outputBlock": 166663
  },
  {
    "inputBlock": 166664,
    "outputBlock": 166763
  },
  {
    "inputBlock": 166764,
    "outputBlock": 166863
  },
  {
    "inputBlock": 166864,
    "outputBlock": 166963
  },
  {
    "inputBlock": 166964,
    "outputBlock": 167063
  },
  {
    "inputBlock": 167064,
    "outputBlock": 167163
  },
  {
    "inputBlock": 167164,
    "outputBlock": 167263
  },
  {
    "inputBlock": 167264,
    "outputBlock": 167363
  },
  {
    "inputBlock": 167364,
    "outputBlock": 167463
  },
  {
    "inputBlock": 167464,
    "outputBlock": 167563
  },
  {
    "inputBlock": 167564,
    "outputBlock": 167663
  },
  {
    "inputBlock": 167664,
    "outputBlock": 167763
  },
  {
    "inputBlock": 167764,
    "outputBlock": 167863
  },
  {
    "inputBlock": 167864,
    "outputBlock": 167963
  },
  {
    "inputBlock": 167964,
    "outputBlock": 168063
  },
  {
    "inputBlock": 168064,
    "outputBlock": 168163
  },
  {
    "inputBlock": 168164,
    "outputBlock": 168263
  },
  {
    "inputBlock": 168264,
    "outputBlock": 168363
  },
  {
    "inputBlock": 168364,
    "outputBlock": 168463
  },
  {
    "inputBlock": 168464,
    "outputBlock": 168563
  },
  {
    "inputBlock": 168564,
    "outputBlock": 168663
  },
  {
    "inputBlock": 168664,
    "outputBlock": 168763
  },
  {
    "inputBlock": 168764,
    "outputBlock": 168863
  },
  {
    "inputBlock": 168864,
    "outputBlock": 168963
  },
  {
    "inputBlock": 168964,
    "outputBlock": 169063
  },
  {
    "inputBlock": 169064,
    "outputBlock": 169163
  },
  {
    "inputBlock": 169164,
    "outputBlock": 169263
  },
  {
    "inputBlock": 169264,
    "outputBlock": 169363
  },
  {
    "inputBlock": 169364,
    "outputBlock": 169463
  },
  {
    "inputBlock": 169464,
    "outputBlock": 169563
  },
  {
    "inputBlock": 169564,
    "outputBlock": 169663
  },
  {
    "inputBlock": 169664,
    "outputBlock": 169763
  },
  {
    "inputBlock": 169764,
    "outputBlock": 169863
  },
  {
    "inputBlock": 169864,
    "outputBlock": 169963
  },
  {
    "inputBlock": 169964,
    "outputBlock": 170063
  },
  {
    "inputBlock": 170064,
    "outputBlock": 170163
  },
  {
    "inputBlock": 170164,
    "outputBlock": 170263
  },
  {
    "inputBlock": 170264,
    "outputBlock": 170363
  },
  {
    "inputBlock": 170364,
    "outputBlock": 170463
  },
  {
    "inputBlock": 170464,
    "outputBlock": 170563
  },
  {
    "inputBlock": 170564,
    "outputBlock": 170663
  },
  {
    "inputBlock": 170664,
    "outputBlock": 170763
  },
  {
    "inputBlock": 170764,
    "outputBlock": 170863
  },
  {
    "inputBlock": 170864,
    "outputBlock": 170963
  },
  {
    "inputBlock": 170964,
    "outputBlock": 171063
  },
  {
    "inputBlock": 171064,
    "outputBlock": 171163
  },
  {
    "inputBlock": 171164,
    "outputBlock": 171263
  },
  {
    "inputBlock": 171264,
    "outputBlock": 171363
  },
  {
    "inputBlock": 171364,
    "outputBlock": 171463
  },
  {
    "inputBlock": 171464,
    "outputBlock": 171563
  },
  {
    "inputBlock": 171564,
    "outputBlock": 171663
  },
  {
    "inputBlock": 171664,
    "outputBlock": 171763
  },
  {
    "inputBlock": 171764,
    "outputBlock": 171863
  },
  {
    "inputBlock": 171864,
    "outputBlock": 171963
  },
  {
    "inputBlock": 171964,
    "outputBlock": 172063
  },
  {
    "inputBlock": 172064,
    "outputBlock": 172163
  },
  {
    "inputBlock": 172164,
    "outputBlock": 172263
  },
  {
    "inputBlock": 172264,
    "outputBlock": 172363
  },
  {
    "inputBlock": 172364,
    "outputBlock": 172463
  },
  {
    "inputBlock": 172464,
    "outputBlock": 172563
  },
  {
    "inputBlock": 172564,
    "outputBlock": 172663
  },
  {
    "inputBlock": 172664,
    "outputBlock": 172763
  },
  {
    "inputBlock": 172764,
    "outputBlock": 172863
  },
  {
    "inputBlock": 172864,
    "outputBlock": 172963
  },
  {
    "inputBlock": 172964,
    "outputBlock": 173063
  },
  {
    "inputBlock": 173064,
    "outputBlock": 173163
  },
  {
    "inputBlock": 173164,
    "outputBlock": 173263
  },
  {
    "inputBlock": 173264,
    "outputBlock": 173363
  },
  {
    "inputBlock": 173364,
    "outputBlock": 173463
  },
  {
    "inputBlock": 173464,
    "outputBlock": 173563
  },
  {
    "inputBlock": 173564,
    "outputBlock": 173663
  },
  {
    "inputBlock": 173664,
    "outputBlock": 173763
  },
  {
    "inputBlock": 173764,
    "outputBlock": 173863
  },
  {
    "inputBlock": 173864,
    "outputBlock": 173963
  },
  {
    "inputBlock": 173964,
    "outputBlock": 174063
  },
  {
    "inputBlock": 174064,
    "outputBlock": 174163
  },
  {
    "inputBlock": 174164,
    "outputBlock": 174178
  }
]